[
    {
        "name": "Abhishek Srivastava",
        "email": "abhishek.srivastava@progressivecare.in",
        "phone": "+91-9876500091",
        "password": "DrSrivastava@PC21",
        "fees": 800,
        "hospital": "cmas87dfy0011i0mozf627j3m"
    },
    {
        "name": "Monica Mallik",
        "email": "monica.mallik@progressivecare.in",
        "phone": "+91-9876500092",
        "password": "DrMallik#PC22",
        "fees": 825,
        "hospital": "cmas87dfy0011i0mozf627j3m"
    },
    {
        "name": "Vikas Vashisht",
        "email": "vikas.vashisht@progressivecare.in",
        "phone": "+91-9876500093",
        "password": "DrVashisht@23PC",
        "fees": 775,
        "hospital": "cmas87dfy0011i0mozf627j3m"
    },
    {
        "name": "Sunita Oberoi",
        "email": "sunita.oberoi@progressivecare.in",
        "phone": "+91-9876500094",
        "password": "DrOberoi!PC24",
        "fees": 850,
        "hospital": "cmas87dfy0011i0mozf627j3m"
    },
    {
        "name": "Arun Aggarwal",
        "email": "arun.aggarwal@progressivecare.in",
        "phone": "+91-9876500095",
        "password": "DrAggarwal@PC25",
        "fees": 810,
        "hospital": "cmas87dfy0011i0mozf627j3m"
    },
    {
        "name": "Varsha Menon",
        "email": "varsha.menon@compassionatemedical.co.in",
        "phone": "+91-9876500096",
        "password": "DrMenon@CM21",
        "fees": 500,
        "hospital": "cmas87fwu0013i0moyk6nkvt3"
    },
    {
        "name": "Girish Rawat",
        "email": "girish.rawat@compassionatemedical.co.in",
        "phone": "+91-9876500097",
        "password": "DrRawat#CM22",
        "fees": 525,
        "hospital": "cmas87fwu0013i0moyk6nkvt3"
    },
    {
        "name": "Kavya Mohan",
        "email": "kavya.mohan@compassionatemedical.co.in",
        "phone": "+91-9876500098",
        "password": "DrMohan@23CM",
        "fees": 475,
        "hospital": "cmas87fwu0013i0moyk6nkvt3"
    },
    {
        "name": "Lalit Bedi",
        "email": "lalit.bedi@compassionatemedical.co.in",
        "phone": "+91-9876500099",
        "password": "DrBedi!CM24",
        "fees": 550,
        "hospital": "cmas87fwu0013i0moyk6nkvt3"
    },
    {
        "name": "Meenakshi Raina",
        "email": "meenakshi.raina@compassionatemedical.co.in",
        "phone": "+91-9876500100",
        "password": "DrRaina@CM25",
        "fees": 510,
        "hospital": "cmas87fwu0013i0moyk6nkvt3"
    },
    {
        "name": "Sandeep Bhargava",
        "email": "sandeep.bhargava@victorymemorial.com",
        "phone": "+91-9876500101",
        "password": "DrBhargava@VM21",
        "fees": 950,
        "hospital": "cmas87hic0015i0motaj0gy2k"
    },
    {
        "name": "Chitra Sahu",
        "email": "chitra.sahu@victorymemorial.com",
        "phone": "+91-9876500102",
        "password": "DrSahu#VM22",
        "fees": 975,
        "hospital": "cmas87hic0015i0motaj0gy2k"
    },
    {
        "name": "Rajeev Kothari",
        "email": "rajeev.kothari@victorymemorial.com",
        "phone": "+91-9876500103",
        "password": "DrKothari@23VM",
        "fees": 925,
        "hospital": "cmas87hic0015i0motaj0gy2k"
    },
    {
        "name": "Shalini Goel",
        "email": "shalini.goel@victorymemorial.com",
        "phone": "+91-9876500104",
        "password": "DrGoel!VM24",
        "fees": 995,
        "hospital": "cmas87hic0015i0motaj0gy2k"
    },
    {
        "name": "Pranav Khandelwal",
        "email": "pranav.khandelwal@victorymemorial.com",
        "phone": "+91-9876500105",
        "password": "DrKhandelwal@VM25",
        "fees": 960,
        "hospital": "cmas87hic0015i0motaj0gy2k"
    },
    {
        "name": "Nandini Prasad",
        "email": "nandini.prasad@horizonhealth.org",
        "phone": "+91-9876500106",
        "password": "DrPrasad@HH21",
        "fees": 650,
        "hospital": "cmas87izb0017i0mobh9klzba"
    },
    {
        "name": "Rajendra Kulkarni",
        "email": "rajendra.kulkarni@horizonhealth.org",
        "phone": "+91-9876500107",
        "password": "DrKulkarni#HH22",
        "fees": 675,
        "hospital": "cmas87izb0017i0mobh9klzba"
    },
    {
        "name": "Sona Basu",
        "email": "sona.basu@horizonhealth.org",
        "phone": "+91-9876500108",
        "password": "DrBasu@23HH",
        "fees": 625,
        "hospital": "cmas87izb0017i0mobh9klzba"
    },
    {
        "name": "Vikrant Desai",
        "email": "vikrant.desai@horizonhealth.org",
        "phone": "+91-9876500109",
        "password": "DrDesai!HH24",
        "fees": 700,
        "hospital": "cmas87izb0017i0mobh9klzba"
    },
    {
        "name": "Anjana Natarajan",
        "email": "anjana.natarajan@horizonhealth.org",
        "phone": "+91-9876500110",
        "password": "DrNatarajan@HH25",
        "fees": 660,
        "hospital": "cmas87izb0017i0mobh9klzba"
    },
    {
        "name": "Alisha Khullar",
        "email": "alisha.khullar@noblecare.net",
        "phone": "+91-9876500111",
        "password": "DrKhullar@NC21",
        "fees": 400,
        "hospital": "cmas87kfn0019i0mog3rh6v2q"
    },
    {
        "name": "Gautam Seth",
        "email": "gautam.seth@noblecare.net",
        "phone": "+91-9876500112",
        "password": "DrSeth#NC22",
        "fees": 425,
        "hospital": "cmas87kfn0019i0mog3rh6v2q"
    },
    {
        "name": "Bhavna Gill",
        "email": "bhavna.gill@noblecare.net",
        "phone": "+91-9876500113",
        "password": "DrGill@23NC",
        "fees": 375,
        "hospital": "cmas87kfn0019i0mog3rh6v2q"
    },
    {
        "name": "Sachin Mehra",
        "email": "sachin.mehra@noblecare.net",
        "phone": "+91-9876500114",
        "password": "DrMehra!NC24",
        "fees": 450,
        "hospital": "cmas87kfn0019i0mog3rh6v2q"
    },
    {
        "name": "Kiran Naidu",
        "email": "kiran.naidu@noblecare.net",
        "phone": "+91-9876500115",
        "password": "DrNaidu@NC25",
        "fees": 410,
        "hospital": "cmas87kfn0019i0mog3rh6v2q"
    },
    {
        "name": "Neeraj Bhatt",
        "email": "neeraj.bhatt@guardianmedical.in",
        "phone": "+91-9876500116",
        "password": "DrBhatt@GM21",
        "fees": 850,
        "hospital": "cmas87lws001bi0mo8bboim25"
    },
    {
        "name": "Sakshi Prakash",
        "email": "sakshi.prakash@guardianmedical.in",
        "phone": "+91-9876500117",
        "password": "DrPrakash#GM22",
        "fees": 875,
        "hospital": "cmas87lws001bi0mo8bboim25"
    },
    {
        "name": "Faiz Ahmed",
        "email": "faiz.ahmed@guardianmedical.in",
        "phone": "+91-9876500118",
        "password": "DrAhmed@23GM",
        "fees": 825,
        "hospital": "cmas87lws001bi0mo8bboim25"
    },
    {
        "name": "Geeta Subramanian",
        "email": "geeta.subramanian@guardianmedical.in",
        "phone": "+91-9876500119",
        "password": "DrSubramanian!GM24",
        "fees": 900,
        "hospital": "cmas87lws001bi0mo8bboim25"
    },
    {
        "name": "Harsh Vardhan",
        "email": "harsh.vardhan@guardianmedical.in",
        "phone": "+91-9876500120",
        "password": "DrVardhan@GM25",
        "fees": 860,
        "hospital": "cmas87lws001bi0mo8bboim25"
    },
    {
        "name": "Pradeep Narang",
        "email": "pradeep.narang@divinehealthcare.co.in",
        "phone": "+91-9876500121",
        "password": "DrNarang@DH21",
        "fees": 550,
        "hospital": "cmas87ncl001di0mord9irrc8"
    },
    {
        "name": "Suman Chauhan",
        "email": "suman.chauhan@divinehealthcare.co.in",
        "phone": "+91-9876500122",
        "password": "DrChauhan#DH22",
        "fees": 575,
        "hospital": "cmas87ncl001di0mord9irrc8"
    },
    {
        "name": "Rakesh Talwar",
        "email": "rakesh.talwar@divinehealthcare.co.in",
        "phone": "+91-9876500123",
        "password": "DrTalwar@23DH",
        "fees": 525,
        "hospital": "cmas87ncl001di0mord9irrc8"
    },
    {
        "name": "Jagriti Sharma",
        "email": "jagriti.sharma@divinehealthcare.co.in",
        "phone": "+91-9876500124",
        "password": "DrSharma!DH24",
        "fees": 590,
        "hospital": "cmas87ncl001di0mord9irrc8"
    },
    {
        "name": "Manoj Grover",
        "email": "manoj.grover@divinehealthcare.co.in",
        "phone": "+91-9876500125",
        "password": "DrGrover@DH25",
        "fees": 560,
        "hospital": "cmas87ncl001di0mord9irrc8"
    },
    {
        "name": "Sameer Goswami",
        "email": "sameer.goswami@pinnaclehospital.com",
        "phone": "+91-9876500126",
        "password": "DrGoswami@PH21",
        "fees": 750,
        "hospital": "cmas87ot0001fi0mofm6icne5"
    },
    {
        "name": "Nalini Dubey",
        "email": "nalini.dubey@pinnaclehospital.com",
        "phone": "+91-9876500127",
        "password": "DrDubey#PH22",
        "fees": 775,
        "hospital": "cmas87ot0001fi0mofm6icne5"
    },
    {
        "name": "Raghav Kamra",
        "email": "raghav.kamra@pinnaclehospital.com",
        "phone": "+91-9876500128",
        "password": "DrKamra@23PH",
        "fees": 725,
        "hospital": "cmas87ot0001fi0mofm6icne5"
    },
    {
        "name": "Poonam Kaushik",
        "email": "poonam.kaushik@pinnaclehospital.com",
        "phone": "+91-9876500129",
        "password": "DrKaushik!PH24",
        "fees": 800,
        "hospital": "cmas87ot0001fi0mofm6icne5"
    },
    {
        "name": "Abhay Nagpal",
        "email": "abhay.nagpal@pinnaclehospital.com",
        "phone": "+91-9876500130",
        "password": "DrNagpal@PH25",
        "fees": 760,
        "hospital": "cmas87ot0001fi0mofm6icne5"
    },
    {
        "name": "Heena Rastogi",
        "email": "heena.rastogi@serenitymedical.org",
        "phone": "+91-9876500131",
        "password": "DrRastogi@SM21",
        "fees": 350,
        "hospital": "cmas87qgi001hi0mo03lzixru"
    },
    {
        "name": "Vishal Kohli",
        "email": "vishal.kohli@serenitymedical.org",
        "phone": "+91-9876500132",
        "password": "DrKohli#SM22",
        "fees": 375,
        "hospital": "cmas87qgi001hi0mo03lzixru"
    },
    {
        "name": "Ayesha Khan",
        "email": "ayesha.khan@serenitymedical.org",
        "phone": "+91-9876500133",
        "password": "DrKhan@23SM",
        "fees": 325,
        "hospital": "cmas87qgi001hi0mo03lzixru"
    },
    {
        "name": "Lokesh Taneja",
        "email": "lokesh.taneja@serenitymedical.org",
        "phone": "+91-9876500134",
        "password": "DrTaneja!SM24",
        "fees": 400,
        "hospital": "cmas87qgi001hi0mo03lzixru"
    },
    {
        "name": "Vidya Chaudhary",
        "email": "vidya.chaudhary@serenitymedical.org",
        "phone": "+91-9876500135",
        "password": "DrChaudhary@SM25",
        "fees": 360,
        "hospital": "cmas87qgi001hi0mo03lzixru"
    },
    {
        "name": "Keshav Bhatia",
        "email": "keshav.bhatia@faithmemorial.net",
        "phone": "+91-9876500136",
        "password": "DrBhatia@FM21",
        "fees": 900,
        "hospital": "cmas87rwi001ji0moc88r9tm6"
    },
    {
        "name": "Deepti Khare",
        "email": "deepti.khare@faithmemorial.net",
        "phone": "+91-9876500137",
        "password": "DrKhare#FM22",
        "fees": 925,
        "hospital": "cmas87rwi001ji0moc88r9tm6"
    },
    {
        "name": "Rishabh Jha",
        "email": "rishabh.jha@faithmemorial.net",
        "phone": "+91-9876500138",
        "password": "DrJha@23FM",
        "fees": 875,
        "hospital": "cmas87rwi001ji0moc88r9tm6"
    },
    {
        "name": "Yamini Sabharwal",
        "email": "yamini.sabharwal@faithmemorial.net",
        "phone": "+91-9876500139",
        "password": "DrSabharwal!FM24",
        "fees": 950,
        "hospital": "cmas87rwi001ji0moc88r9tm6"
    },
    {
        "name": "Shashank Mitra",
        "email": "shashank.mitra@faithmemorial.net",
        "phone": "+91-9876500140",
        "password": "DrMitra@FM25",
        "fees": 910,
        "hospital": "cmas87rwi001ji0moc88r9tm6"
    },
    {
        "name": "Mohini Guha",
        "email": "mohini.guha@tranquilcare.in",
        "phone": "+91-9876500141",
        "password": "DrGuha@TC21",
        "fees": 450,
        "hospital": "cmas87tbs001li0morzcm4mcr"
    },
    {
        "name": "Amit Khater",
        "email": "amit.khater@tranquilcare.in",
        "phone": "+91-9876500142",
        "password": "DrKhater#TC22",
        "fees": 475,
        "hospital": "cmas87tbs001li0morzcm4mcr"
    },
    {
        "name": "Pooja Nanda",
        "email": "pooja.nanda@tranquilcare.in",
        "phone": "+91-9876500143",
        "password": "DrNanda@23TC",
        "fees": 425,
        "hospital": "cmas87tbs001li0morzcm4mcr"
    },
    {
        "name": "Sudhir Kansal",
        "email": "sudhir.kansal@tranquilcare.in",
        "phone": "+91-9876500144",
        "password": "DrKansal!TC24",
        "fees": 490,
        "hospital": "cmas87tbs001li0morzcm4mcr"
    },
    {
        "name": "Ridhi Arora",
        "email": "ridhi.arora@tranquilcare.in",
        "phone": "+91-9876500145",
        "password": "DrArora@TC25",
        "fees": 460,
        "hospital": "cmas87tbs001li0morzcm4mcr"
    },
    {
        "name": "Kamal Dhillon",
        "email": "kamal.dhillon@evergreenhospital.co.in",
        "phone": "+91-9876500146",
        "password": "DrDhillon@EH21",
        "fees": 800,
        "hospital": "cmas87urh001ni0mokb2u3hsy"
    },
    {
        "name": "Renu Kalra",
        "email": "renu.kalra@evergreenhospital.co.in",
        "phone": "+91-9876500147",
        "password": "DrKalra#EH22",
        "fees": 825,
        "hospital": "cmas87urh001ni0mokb2u3hsy"
    },
    {
        "name": "Dinesh Chandna",
        "email": "dinesh.chandna@evergreenhospital.co.in",
        "phone": "+91-9876500148",
        "password": "DrChandna@23EH",
        "fees": 775,
        "hospital": "cmas87urh001ni0mokb2u3hsy"
    },
    {
        "name": "Sarita Ahuja",
        "email": "sarita.ahuja@evergreenhospital.co.in",
        "phone": "+91-9876500149",
        "password": "DrAhuja!EH24",
        "fees": 850,
        "hospital": "cmas87urh001ni0mokb2u3hsy"
    },
    {
        "name": "Yogesh Lalwani",
        "email": "yogesh.lalwani@evergreenhospital.co.in",
        "phone": "+91-9876500150",
        "password": "DrLalwani@EH25",
        "fees": 810,
        "hospital": "cmas87urh001ni0mokb2u3hsy"
    },
    {
        "name": "Aisha Patel",
        "email": "apatel@example-med.in",
        "phone": "(+91) 98765-43210",
        "fees": 1500,
        "password": "DummyPass123",
        "hospital": "cmas86pjq0001i0mojwsu1zob"
    },
    {
        "name": "Rajesh Kumar",
        "email": "rkumar@example-med.in",
        "phone": "(+91) 98765-43211",
        "fees": 1800,
        "password": "DummyPass124",
        "hospital" : "cmas86pjq0001i0mojwsu1zob"
    },
    {
        "name": "Priya Sharma",
        "email": "psharma@example-med.in",
        "phone": "(+91) 98765-43212",
        "fees": 2000,
        "password": "DummyPass125",
        "hospital": "cmas86pjq0001i0mojwsu1zob"
    },
    {
        "name": "Vikram Singh",
        "email": "vsingh@example-med.in",
        "phone": "(+91) 98765-43213",
        "fees": 1700,
        "password": "DummyPass126",
        "hospital": "cmas86pjq0001i0mojwsu1zob"
    },
    {
        "name": "Deepa Agarwal",
        "email": "dagarwal@example-med.in",
        "phone": "(+91) 98765-43214",
        "fees": 2200,
        "password": "DummyPass127",
        "hospital": "cmas86pjq0001i0mojwsu1zob"
    },
    {
        "name": "Sanjay Gupta",
        "email": "sgupta@example-med.in",
        "phone": "(+91) 98765-43215",
        "fees": 1900,
        "password": "DummyPass128",
        "hospital": "cmas86rcn0003i0movelqovzd"
    },
    {
        "name": "Meera Reddy",
        "email": "mreddy@example-med.in",
        "phone": "(+91) 98765-43216",
        "fees": 1600,
        "password": "DummyPass129",
        "hospital": "cmas86rcn0003i0movelqovzd"
    },
    {
        "name": "Anand Desai",
        "email": "adesai@example-med.in",
        "phone": "(+91) 98765-43217",
        "fees": 2100,
        "password": "DummyPass130",
        "hospital": "cmas86rcn0003i0movelqovzd"
    },
    {
        "name": "Lakshmi Nair",
        "email": "lnair@example-med.in",
        "phone": "(+91) 98765-43218",
        "fees": 1850,
        "password": "DummyPass131",
        "hospital": "cmas86rcn0003i0movelqovzd"
    },
    {
        "name": "Arjun Mehta",
        "email": "amehta@example-med.in",
        "phone": "(+91) 98765-43219",
        "fees": 2300,
        "password": "DummyPass132",
        "hospital": "cmas86rcn0003i0movelqovzd"
    },
    {
        "name": "Kavita Joshi",
        "email": "kjoshi@example-med.in",
        "phone": "(+91) 98765-43220",
        "fees": 1750,
        "password": "DummyPass133",
        "hospital": "cmas86smf0005i0mogevo4ta7"
    },
    {
        "name": "Nikhil Verma",
        "email": "nverma@example-med.in",
        "phone": "(+91) 98765-43221",
        "fees": 2000,
        "password": "DummyPass134",
        "hospital": "cmas86smf0005i0mogevo4ta7"
    },
    {
        "name": "Sunita Choudhary",
        "email": "schoudhary@example-med.in",
        "phone": "(+91) 98765-43222",
        "fees": 1950,
        "password": "DummyPass135",
        "hospital": "cmas86smf0005i0mogevo4ta7"
    },
    {
        "name": "Amit Malhotra",
        "email": "amalhotra@example-med.in",
        "phone": "(+91) 98765-43223",
        "fees": 2200,
        "password": "DummyPass136",
        "hospital": "cmas86smf0005i0mogevo4ta7"
    },
    {
        "name": "Neha Iyer",
        "email": "niyer@example-med.in",
        "phone": "(+91) 98765-43224",
        "fees": 1800,
        "password": "DummyPass137",
        "hospital": "cmas86smf0005i0mogevo4ta7"
    },
    {
        "name": "Rahul Banerjee",
        "email": "rbanerjee@example-med.in",
        "phone": "(+91) 98765-43225",
        "fees": 2100,
        "password": "DummyPass138",
        "hospital": "cmas86twk0007i0mooe5vwd4f"
    },
    {
        "name": "Pooja Kapoor",
        "email": "pkapoor@example-med.in",
        "phone": "(+91) 98765-43226",
        "fees": 1650,
        "password": "DummyPass139",
        "hospital": "cmas86twk0007i0mooe5vwd4f"
    },
    {
        "name": "Vivek Mishra",
        "email": "vmishra@example-med.in",
        "phone": "(+91) 98765-43227",
        "fees": 2250,
        "password": "DummyPass140",
        "hospital": "cmas86twk0007i0mooe5vwd4f"
    },
    {
        "name": "Anjali Rao",
        "email": "arao@example-med.in",
        "phone": "(+91) 98765-43228",
        "fees": 1900,
        "password": "DummyPass141",
        "hospital": "cmas86twk0007i0mooe5vwd4f"
    },
    {
        "name": "Karan Bhatia",
        "email": "kbhatia@example-med.in",
        "phone": "(+91) 98765-43229",
        "fees": 2050,
        "password": "DummyPass142",
        "hospital": "cmas86twk0007i0mooe5vwd4f"
    },
    {
        "name": "Divya Chauhan",
        "email": "dchauhan@example-med.in",
        "phone": "(+91) 98765-43230",
        "fees": 1750,
        "password": "DummyPass143",
        "hospital": "cmas86wgg000bi0molgrgjq40"
    },
    {
        "name": "Suresh Pillai",
        "email": "spillai@example-med.in",
        "phone": "(+91) 98765-43231",
        "fees": 2150,
        "password": "DummyPass144",
        "hospital": "cmas86wgg000bi0molgrgjq40"
    }
]
